LICENSE
README.md
setup.py
ez_wsi_dicomweb/__init__.py
ez_wsi_dicomweb/base_patch.py
ez_wsi_dicomweb/credential_factory.py
ez_wsi_dicomweb/credential_factory_test.py
ez_wsi_dicomweb/dicom_frame_decoder.py
ez_wsi_dicomweb/dicom_frame_decoder_test.py
ez_wsi_dicomweb/dicom_slide.py
ez_wsi_dicomweb/dicom_slide_test.py
ez_wsi_dicomweb/dicom_store.py
ez_wsi_dicomweb/dicom_store_test.py
ez_wsi_dicomweb/dicom_web_interface.py
ez_wsi_dicomweb/dicom_web_interface_test.py
ez_wsi_dicomweb/dicomweb_credential_factory.py
ez_wsi_dicomweb/embedding_metrics.py
ez_wsi_dicomweb/embedding_metrics_test.py
ez_wsi_dicomweb/error_retry_util.py
ez_wsi_dicomweb/ez_wsi_errors.py
ez_wsi_dicomweb/ez_wsi_errors_test.py
ez_wsi_dicomweb/ez_wsi_logging_factory.py
ez_wsi_dicomweb/ez_wsi_logging_factory_test.py
ez_wsi_dicomweb/gcs_image.py
ez_wsi_dicomweb/gcs_image_test.py
ez_wsi_dicomweb/image_util.py
ez_wsi_dicomweb/local_dicom_file_interface.py
ez_wsi_dicomweb/local_dicom_slide_cache.py
ez_wsi_dicomweb/local_dicom_slide_cache_test.py
ez_wsi_dicomweb/local_dicom_slide_cache_types.py
ez_wsi_dicomweb/local_image.py
ez_wsi_dicomweb/local_image_test.py
ez_wsi_dicomweb/magnification.py
ez_wsi_dicomweb/magnification_test.py
ez_wsi_dicomweb/patch_embedding.py
ez_wsi_dicomweb/patch_embedding_endpoints.py
ez_wsi_dicomweb/patch_embedding_endpoints_test.py
ez_wsi_dicomweb/patch_embedding_ensemble_methods.py
ez_wsi_dicomweb/patch_embedding_ensemble_methods_test.py
ez_wsi_dicomweb/patch_embedding_test.py
ez_wsi_dicomweb/patch_embedding_types.py
ez_wsi_dicomweb/patch_embedding_types_test.py
ez_wsi_dicomweb/patch_generator.py
ez_wsi_dicomweb/patch_generator_test.py
ez_wsi_dicomweb/pixel_spacing.py
ez_wsi_dicomweb/pixel_spacing_converter.py
ez_wsi_dicomweb/pixel_spacing_converter_test.py
ez_wsi_dicomweb/pixel_spacing_test.py
ez_wsi_dicomweb/slide_level_map.py
ez_wsi_dicomweb/slide_level_map_test.py
ez_wsi_dicomweb.egg-info/PKG-INFO
ez_wsi_dicomweb.egg-info/SOURCES.txt
ez_wsi_dicomweb.egg-info/dependency_links.txt
ez_wsi_dicomweb.egg-info/requires.txt
ez_wsi_dicomweb.egg-info/top_level.txt
ez_wsi_dicomweb/ml_toolkit/__init__.py
ez_wsi_dicomweb/ml_toolkit/dicom_builder.py
