Metadata-Version: 2.4
Name: ez_wsi_dicomweb
Version: 6.1.5
Summary: A library that provides the ability to extract an image patch from a pathology DICOM whole slide image.
Home-page: https://github.com/GoogleCloudPlatform/ez-wsi-dicomweb
Author: Google LLC.
Author-email: no-reply@google.com
License: Apache 2.0
Requires-Python: >=3.10
License-File: LICENSE
Requires-Dist: absl-py
Requires-Dist: cachetools
Requires-Dist: dataclasses-json
Requires-Dist: google-auth
Requires-Dist: google_auth_httplib2
Requires-Dist: google_cloud_storage
Requires-Dist: imagecodecs
Requires-Dist: numpy
Requires-Dist: opencv-python-headless
Requires-Dist: pillow
Requires-Dist: psutil
Requires-Dist: pydicom
Requires-Dist: requests
Requires-Dist: requests_mock
Requires-Dist: requests_toolbelt
Requires-Dist: retrying
Dynamic: author
Dynamic: author-email
Dynamic: home-page
Dynamic: license
Dynamic: license-file
Dynamic: requires-dist
Dynamic: requires-python
Dynamic: summary
